dzwl/__init__.py
dzwl/airtest_util.py
dzwl/fun_util.py
dzwl/interface_util.py
dzwl-20240809.dist-info/METADATA
dzwl-20240809.dist-info/WHEEL
dzwl-20240809.dist-info/top_level.txt
dzwl-20240809.dist-info/RECORD
