Metadata-Version: 2.1
Name: dzwl
Version: 20240809
Summary: PyPI Tutorial
Author: zj
Author-email: author@example.com
Requires-Python: >=3
